tracefunc/__init__.py
tracefunc/_modidx.py
tracefunc/core.py
tracefunc-0.0.6.dist-info/licenses/LICENSE
tracefunc-0.0.6.dist-info/METADATA
tracefunc-0.0.6.dist-info/WHEEL
tracefunc-0.0.6.dist-info/entry_points.txt
tracefunc-0.0.6.dist-info/top_level.txt
tracefunc-0.0.6.dist-info/RECORD
