Metadata-Version: 2.4
Name: tracefunc
Version: 0.0.6
Summary: AST-level execution tracing via sys.monitoring
Home-page: https://github.com/AnswerDotAI/tracefunc
Author: Jeremy Howard
Author-email: github@jhoward.fastmail.fm
License: Apache Software License 2.0
Keywords: nbdev jupyter notebook python
Classifier: Development Status :: 4 - Beta
Classifier: Intended Audience :: Developers
Classifier: Natural Language :: English
Classifier: Programming Language :: Python :: 3.12
Classifier: License :: OSI Approved :: Apache Software License
Requires-Python: >=3.12
License-File: LICENSE
Provides-Extra: dev
Dynamic: author
Dynamic: author-email
Dynamic: classifier
Dynamic: description
Dynamic: description-content-type
Dynamic: home-page
Dynamic: keywords
Dynamic: license
Dynamic: license-file
Dynamic: provides-extra
Dynamic: requires-python
Dynamic: summary
